pysm/__init__.py
pysm/pysm.py
pysm/version.py
pysm-0.3.9.dist-info/DESCRIPTION.rst
pysm-0.3.9.dist-info/METADATA
pysm-0.3.9.dist-info/RECORD
pysm-0.3.9.dist-info/WHEEL
pysm-0.3.9.dist-info/metadata.json
pysm-0.3.9.dist-info/top_level.txt
